<XMLLevel CollectableMonster="" HideCallout="4" LettersGroup="3" SegmentTime="12" StoneType="1" monsterInputType="SoundWord">
	<Segments>
		<Segment SegmentTime="12" spawnIds="19,83,18,82">
			
			<MonsterRequiredLetters>
				<string>t</string>
				<string>s</string>
			<string>h</string><string>i</string><string>ṅ</string><string>i</string><string>n</string><string>a</string></MonsterRequiredLetters>
			<MonsterAllLetters>
			</MonsterAllLetters>
			<Stones>
				<string>t</string>
				<string>s</string>
				<string>h</string>
				<string>i</string>
			<string spawnId="30">ṅ</string><string spawnId="30">i</string><string spawnId="30">n</string><string spawnId="28">a</string></Stones>
    </Segment>
	<Segment SegmentTime="12" spawnIds="25,28,91,92">
		
		<MonsterRequiredLetters>
			<string>i</string>
			<string>t</string>
			<string>h</string>
		<string>u</string></MonsterRequiredLetters>
		<MonsterAllLetters>
		</MonsterAllLetters>
		<Stones>
			<string>i</string>
			<string>t</string>
			<string>h</string>
			<string>u</string>
		</Stones>
    </Segment>
	<Segment SegmentTime="12" spawnIds="4,5,54,55">
		
		<MonsterRequiredLetters>
			<string>ṅ</string>
			<string>u</string>
		<string>ṅ</string><string>u</string><string>n</string><string>a</string></MonsterRequiredLetters>
		<MonsterAllLetters>
		</MonsterAllLetters>
		<Stones>
			<string>ṅ</string>
			<string>u</string>
			<string>ṅ</string>
			<string>u</string>
		<string spawnId="20">n</string><string spawnId="24">a</string></Stones>
    </Segment>
	<Segment SegmentTime="12" spawnIds="70,71,56,57">
		
		<MonsterRequiredLetters>
			<string>ḽ</string>
			<string>i</string>
			<string>ḓ</string>
		<string>u</string></MonsterRequiredLetters>
		<MonsterAllLetters>
		</MonsterAllLetters>
		<Stones>
			<string>ḽ</string>
			<string>i</string>
			<string>ḓ</string>     
			<string>u</string>
		</Stones>
	</Segment>
	<Segment SegmentTime="12" spawnIds="9,96,8,95">
		
		<MonsterRequiredLetters>
			<string>i</string>
			<string>ḓ</string>
			<string>u</string>
		</MonsterRequiredLetters>
		<MonsterAllLetters>
		</MonsterAllLetters>
		<Stones>
			<string>z</string>
			<string>i</string>
			<string>ḓ</string>
			<string>u</string>
		</Stones>
    </Segment>
  </Segments>
</XMLLevel>