<XMLLevel CollectableMonster="" HideCallout="1" LettersGroup="10" SegmentTime="9" StoneType="1" monsterInputType="Letter">
  <Segments>
    <Segment SegmentTime="9" spawnIds="">
      
	  <MonsterRequiredLetters>
		<string>स</string>
	  </MonsterRequiredLetters>
	  <MonsterAllLetters>
	  </MonsterAllLetters>
	  <Stones>
        <string spawnId="4">ख</string>
        <string spawnId="74">ख</string>
        <string spawnId="87">ख</string>
		<string spawnId="23">ऐ</string>
		<string spawnId="60">ऐ</string>
		<string spawnId="5">ख</string>
		<string spawnId="86">ऐ</string>
		<string spawnId="20">ऐ</string>
		<string spawnId="75">स</string>
      </Stones>
    </Segment>
	<Segment SegmentTime="9" spawnIds="">
      
	  <MonsterRequiredLetters>
		<string>ड</string>
	  </MonsterRequiredLetters>
	  <MonsterAllLetters>
	  </MonsterAllLetters>
	  <Stones>
        <string spawnId="71">ड़</string>
        <string spawnId="70">ख</string>
        <string spawnId="76">ट</string>
		<string spawnId="88">स</string>
		<string spawnId="21">ध</string>
		<string spawnId="3">ऐ</string>
		<string spawnId="85">ड़</string>
		<string spawnId="22">ह्</string>
		<string spawnId="73">स</string>
		<string spawnId="2">ड</string>
	 </Stones>
    </Segment>
	<Segment SegmentTime="9" spawnIds="4,74,87,23,60,5,86,20,75">
      
	  <MonsterRequiredLetters>
		<string>ड</string>
	  </MonsterRequiredLetters>
	  <MonsterAllLetters>
	  </MonsterAllLetters>
	  <Stones>
        <string>ट</string>
        <string>ख</string>
        <string>ख</string>
		<string>ख</string>
		<string>ऐ</string>
		<string>ऐ</string>
		<string>ऐ</string>
		<string>ख</string>
		<string>ड</string>
	  </Stones>
    </Segment>
	<Segment SegmentTime="9" spawnIds="4,74,87,23,60,5,86,20,75">
      
	  <MonsterRequiredLetters>
		<string>ख</string>
	  </MonsterRequiredLetters>
	  <MonsterAllLetters>
	  </MonsterAllLetters>
	  <Stones>
        <string>ऐ</string>
        <string>ह्</string>
        <string>ध</string>
		<string>स</string>
		<string>स</string>
		<string>ह्</string>
		<string>ध</string>
		<string>ह्</string>
		<string>ख</string>
      </Stones>
    </Segment>
	<Segment SegmentTime="9" spawnIds="">
      
	  <MonsterRequiredLetters>
		<string>ऐ</string>
	  </MonsterRequiredLetters>
	  <MonsterAllLetters>
	  </MonsterAllLetters>
	  <Stones>
        <string spawnId="71">ट</string>
        <string spawnId="70">ड़</string>
        <string spawnId="76">ह्</string>
		<string spawnId="88">ध</string>
		<string spawnId="21">ट</string>
		<string spawnId="3">ड़</string>
		<string spawnId="85">ट</string>
		<string spawnId="22">ड़</string>
		<string spawnId="73">ड़</string>
		<string spawnId="2">ऐ</string>
      </Stones>
    </Segment>
  </Segments>
</XMLLevel>