<XMLLevel CollectableMonster="" HideCallout="4" LettersGroup="3" SegmentTime="10" StoneType="2" monsterInputType="LetterInWord">
  <Segments>
    <Segment SegmentTime="10" spawnIds="">
      
	  <MonsterRequiredLetters>
		<string>ঝ</string>
	  </MonsterRequiredLetters>
	  <MonsterAllLetters>
		<string>X</string>
		<string>ি</string>
	  <string>ঁ</string><string>ঝ</string><string>ি</string><string>ঁ</string></MonsterAllLetters>
	  <Stones>
        <string spawnId="14">জ</string>
        <string spawnId="74">ঠ</string>
		<string spawnId="20">ঝ</string>
      </Stones>
    </Segment>
	<Segment SegmentTime="10" spawnIds="">
      
	  <MonsterRequiredLetters>
		<string>ন</string>
	  </MonsterRequiredLetters>
	  <MonsterAllLetters>
		<string>X</string>
		<string>ি</string>
	  <string>জ</string></MonsterAllLetters>
	  <Stones>
        <string spawnId="15">ন</string>
        <string spawnId="75">জ</string>
        <string spawnId="23">ন</string>
      </Stones>
    </Segment>
	<Segment SegmentTime="10" spawnIds="">
      
	  <MonsterRequiredLetters>
		<string>ঝ</string>
	  </MonsterRequiredLetters>
	  <MonsterAllLetters>
		<string>X</string>
		<string>ি</string>
	  <string>ঁ</string><string>ঝ</string><string>ি</string><string>ঁ</string></MonsterAllLetters>
	  <Stones>
        <string spawnId="28">ন</string>
        <string spawnId="94">জ</string>
		<string spawnId="45">ঝ</string>
      </Stones>
    </Segment>
	<Segment SegmentTime="10" spawnIds="">
      
	  <MonsterRequiredLetters>
		<string>ঠ</string>
	  </MonsterRequiredLetters>
	  <MonsterAllLetters>
		<string>X</string>
		<string>ি</string>
		<string>ক</string>
	  </MonsterAllLetters>
	  <Stones>
        <string spawnId="25">ই</string>
        <string spawnId="93">চ</string>
		<string spawnId="36">ঠ</string>
      </Stones>
    </Segment>
	<Segment SegmentTime="10" spawnIds="">
      
	  <MonsterRequiredLetters>
		<string>ঠ</string>
	  </MonsterRequiredLetters>
	  <MonsterAllLetters>
		<string>X</string>
		<string>ি</string>
	  <string>ক</string></MonsterAllLetters>
	  <Stones>
        <string spawnId="78">ই</string>
        <string spawnId="60">ঞ</string>
		<string spawnId="79">ঠ</string>
      </Stones>
    </Segment>
  </Segments>
</XMLLevel>