<XMLLevel CollectableMonster="" HideCallout="1" LettersGroup="6" SegmentTime="12" StoneType="2" monsterInputType="Word">
	<Segments>
		<Segment SegmentTime="12" spawnIds="">
			
			<MonsterRequiredLetters>
				<string>j</string>
				<string>u</string>
				<string>z</string>
			<string>i</string></MonsterRequiredLetters>
			<MonsterAllLetters>
			</MonsterAllLetters>
			<Stones>
				<string spawnId="36">f v sh ny dh</string>
				<string spawnId="65">f v sh ny dh</string>
				<string spawnId="68">o</string>
				<string spawnId="45">j</string>
				<string spawnId="94">u</string>
				<string spawnId="28">z</string>
				<string spawnId="25">i</string>
				<string bonusScore="275" spawnId="93">BonusLetter</string>
			</Stones>
    </Segment>
	<Segment SegmentTime="12" spawnIds="">
		
		<MonsterRequiredLetters>
			<string>j</string>
			<string>u</string>
			<string>z</string>
			<string>i</string>
		</MonsterRequiredLetters>
		<MonsterAllLetters>
		</MonsterAllLetters>
		<Stones>
			<string spawnId="59">o</string>
			<string spawnId="45">o</string>
			<string spawnId="2">f v sh ny dh</string>
			<string spawnId="36">j</string>
			<string spawnId="79">u</string>
			<string spawnId="78">z</string>
			<string spawnId="61">i</string>
			<string bonusScore="275" spawnId="3">BonusLetter</string>
		</Stones>
    </Segment>
	<Segment SegmentTime="12" spawnIds="">
		
		<MonsterRequiredLetters>
			<string>d</string>
			<string>a</string>
			<string>d</string>
		<string>a</string></MonsterRequiredLetters>
		<MonsterAllLetters>
		</MonsterAllLetters>
		<Stones>
			<string spawnId="45">f v sh ny dh</string>
			<string spawnId="68">f v sh ny dh</string>
			<string spawnId="65">f v sh ny dh</string>
			<string spawnId="36">o</string>
			<string spawnId="93">d</string>
			<string spawnId="25">a</string>
			<string spawnId="28">d</string>
			<string spawnId="94">a</string>
		</Stones>
    </Segment>
	<Segment SegmentTime="12" spawnIds="">
		
		<MonsterRequiredLetters>
			<string>d</string>
			<string>a</string>
			<string>d</string>
		<string>a</string></MonsterRequiredLetters>
		<MonsterAllLetters>
		</MonsterAllLetters>
		<Stones>
			<string spawnId="61">f v sh ny dh</string>
			<string spawnId="36">o</string>
			<string spawnId="3">f v sh ny dh</string>
			<string spawnId="45">d</string>
			<string spawnId="78">a</string>
			<string spawnId="79">d</string>
			<string spawnId="59">a</string>
			<string bonusScore="275" spawnId="2">BonusLetter</string>
		</Stones>
	</Segment>
	<Segment SegmentTime="12" spawnIds="">
		
		<MonsterRequiredLetters>
			<string>o</string>
			<string>n</string>
			<string>y</string>
			<string>o</string>
		</MonsterRequiredLetters>
		<MonsterAllLetters>
		</MonsterAllLetters>
		<Stones>
			<string spawnId="11">f v sh ny dh</string>
			<string spawnId="75">f v sh ny dh</string>
			<string spawnId="20">f v sh ny dh</string>
			<string spawnId="59">o</string>
			<string spawnId="74">n</string>
			<string spawnId="12">y</string>
			<string spawnId="23">o</string>
			<string bonusScore="275" spawnId="61">BonusLetter</string>
		</Stones>
    </Segment>
  </Segments>
</XMLLevel>