<XMLLevel CollectableMonster="Knight" HideCallout="3" LettersGroup="7" SegmentTime="10" StoneType="1" monsterInputType="Word">
  <Segments>
    <Segment SegmentTime="10" spawnIds="">
    	
    	<MonsterRequiredLetters>
    		<string>र</string>
    	<string>स</string></MonsterRequiredLetters>
    	<MonsterAllLetters>
    	</MonsterAllLetters>
    	<Stones>
    		<string spawnId="5">क्ष</string>
    		<string spawnId="21">ष</string>
			<string spawnId="86">क्ष</string>
			<string spawnId="75">क्ष</string>
			<string spawnId="4">क्ष</string>
			<string spawnId="87">त्र</string>
			<string spawnId="22">ढ</string>
			<string spawnId="74">र</string>
			<string spawnId="60">स</string>
    	</Stones>
	</Segment>
	<Segment SegmentTime="10" spawnIds="">
		
		<MonsterRequiredLetters>
			<string>क</string>
		<string>ा</string><string>य</string></MonsterRequiredLetters>
	  	<MonsterAllLetters>
	  	</MonsterAllLetters>
	  	<Stones>
        	<string spawnId="95">ढ</string>
        	<string spawnId="12">त्र</string>
        	<string spawnId="54">ढ</string>
        	<string spawnId="96">क्ष</string>
			<string spawnId="69">ज्ञ</string>
			<string spawnId="55">क</string>
			<string spawnId="11">ा</string>
			<string spawnId="72">य</string>
      	</Stones>
    </Segment>
	<Segment SegmentTime="10" spawnIds="4,5,21,22,60,74,75,86,87">
		
      	<MonsterRequiredLetters>
			<string>न</string>
	  	<string>ा</string><string>र</string><string>ा</string><string>ज</string></MonsterRequiredLetters>
	  	<MonsterAllLetters>
	  	</MonsterAllLetters>
	  	<Stones>
			<string>ष</string>
	        <string>ढ</string>
			<string>अः</string>
	        <string>ज्ञ</string>
			<string>न</string>
			<string>ा</string>
			<string>र</string>
			<string>ा</string>
			<string>ज</string>
      	</Stones>
	</Segment>
	<Segment SegmentTime="10" spawnIds="">
		
      	<MonsterRequiredLetters>
			<string>ल</string>
	  	<string>व</string><string>ण</string></MonsterRequiredLetters>
	  	<MonsterAllLetters>
	  	</MonsterAllLetters>
	  	<Stones>
	        <string spawnId="73">ज्ञ</string>
	        <string spawnId="76">ज्ञ</string>
	        <string spawnId="89">ष</string>
			<string spawnId="90">ल</string>
			<string spawnId="93">व</string>
			<string spawnId="94">ण</string>
			<string spawnId="74">Shield</string>
			<string bonusScore="275" spawnId="75">BonusLetter</string>
      	</Stones>
    </Segment>
	<Segment SegmentTime="10" spawnIds="">
		
      	<MonsterRequiredLetters>
			<string>न</string>
	  	<string>ा</string><string>म</string></MonsterRequiredLetters>
	  	<MonsterAllLetters>
	  	</MonsterAllLetters>
	  	<Stones>
	        <string spawnId="60">ढ</string>
	        <string spawnId="74">ढ</string>
			<string spawnId="22">ज्ञ</string>
	        <string spawnId="87">अः</string>
			<string spawnId="4">ढ</string>
			<string spawnId="75">ष</string>
			<string spawnId="86">न</string>
			<string spawnId="21">ा</string>
			<string spawnId="5">म</string>
      	</Stones>
	</Segment>
  </Segments>
</XMLLevel>