<XMLLevel CollectableMonster="" HideCallout="5" LettersGroup="3" SegmentTime="10" StoneType="1" monsterInputType="Letter">
  <Segments>
    <Segment SegmentTime="10" spawnIds="">
    	
    	<MonsterRequiredLetters>
    		<string>ج</string>
    	</MonsterRequiredLetters>
    	<MonsterAllLetters>
    	</MonsterAllLetters>
    	<Stones>
    		<string spawnId="86">ک</string>
    		<string spawnId="75">ک</string>
    		<string spawnId="87">ج</string>
			<string spawnId="93">ج</string>
			<string spawnId="74">ک</string>
			<string spawnId="94">ج</string>
    	</Stones>
	</Segment>
	<Segment SegmentTime="10" spawnIds="86,75,87,93,74,94">
		
		<MonsterRequiredLetters>
			<string>ج</string>
		</MonsterRequiredLetters>
	  	<MonsterAllLetters>
	  	</MonsterAllLetters>
	  	<Stones>
        	<string>ک</string>
        	<string spawnId="30">ج</string><string spawnId="30">ج</string></Stones>
    </Segment>
	<Segment SegmentTime="10" spawnIds="">
		
      	<MonsterRequiredLetters>
			<string>ش</string>
	  	</MonsterRequiredLetters>
	  	<MonsterAllLetters>
	  	</MonsterAllLetters>
	  	<Stones>
			<string spawnId="15">MagnetLetter</string>
			<string bonusScore="275" spawnId="14">BonusLetter</string>
      	<string spawnId="22" /><string spawnId="26">و</string><string spawnId="24">ش</string><string spawnId="20">ج</string><string spawnId="20">ت</string><string spawnId="22">ش</string></Stones>
	</Segment>
	<Segment SegmentTime="10" spawnIds="">
		
      	<MonsterRequiredLetters>
			<string>ش</string>
	  	</MonsterRequiredLetters>
	  	<MonsterAllLetters>
	  	</MonsterAllLetters>
	  	<Stones>
	        <string spawnId="73">ج</string>
	        <string spawnId="76">ش</string>
	        <string spawnId="14">MagnetLetter</string>
			<string bonusScore="275" spawnId="15">BonusLetter</string>
      	<string spawnId="24" /><string spawnId="26">ت</string><string spawnId="24">ت</string><string spawnId="26">ش</string></Stones>
    </Segment>
	<Segment SegmentTime="10" spawnIds="">
		
      	<MonsterRequiredLetters>
			<string>ج</string>
	  	</MonsterRequiredLetters>
	  	<MonsterAllLetters>
	  	</MonsterAllLetters>
	  	<Stones>
	        <string spawnId="65">ش</string>
	        <string spawnId="68">ش</string>
	        <string spawnId="6">ک</string>
			<string spawnId="7">ج</string>
			<string delayIn="0" delayRepet="0" loop="true" spawnId="77,80,77" speed="150">BonusLetter</string>
			<string delayIn="0" delayRepet="0" loop="true" spawnId="24,29,24" speed="150">BonusLetter</string>
      	</Stones>
	</Segment>
  </Segments>
</XMLLevel>