<XMLLevel CollectableMonster="" HideCallout="3" LettersGroup="7" SegmentTime="9" StoneType="1" monsterInputType="SoundWord">
  <Segments>
    <Segment SegmentTime="10" spawnIds="">
    	
    	<MonsterRequiredLetters>
    		<string>म</string>
    	<string>ा</string><string>म</string><string>ा</string></MonsterRequiredLetters>
    	<MonsterAllLetters>
    	</MonsterAllLetters>
    	<Stones>
    		<string spawnId="1">ज्ञ</string>
    		<string spawnId="21">ज्ञ</string>
    		<string spawnId="76">म</string>
			<string spawnId="73">ा</string>
			<string spawnId="22">म</string>
			<string spawnId="0">ा</string>
    	</Stones>
	</Segment>
	<Segment SegmentTime="10" spawnIds="0,1,21,22,73,76">
		
		<MonsterRequiredLetters>
			<string>क</string>
		<string>ा</string><string>न</string></MonsterRequiredLetters>
	  	<MonsterAllLetters>
	  	</MonsterAllLetters>
	  	<Stones>
        	<string>अः</string>
        	<string>ज्ञ</string>
        	<string>ञ</string>
			<string>क</string>
			<string>ा</string>
			<string>न</string>
      	</Stones>
    </Segment>
	<Segment SegmentTime="10" spawnIds="">
		
      	<MonsterRequiredLetters>
			<string>म</string>
	  	<string>ा</string><string>ँ</string></MonsterRequiredLetters>
	  	<MonsterAllLetters>
	  	</MonsterAllLetters>
	  	<Stones>
			<string spawnId="59">त्र</string>
	        <string spawnId="22">ञ</string>
	        <string spawnId="61">त्र</string>
			<string spawnId="18">म</string>
			<string spawnId="21">ा</string>
			<string spawnId="19">ँ</string>
      	</Stones>
	</Segment>
	<Segment SegmentTime="10" spawnIds="18,19,21,22,59,61">
		
      	<MonsterRequiredLetters>
			<string>क</string>
	  	<string>ा</string><string>न</string></MonsterRequiredLetters>
	  	<MonsterAllLetters>
	  	</MonsterAllLetters>
	  	<Stones>
	        <string>क्ष</string>
	        <string>त्र</string>
	        <string>ष</string>
			<string>क</string>
			<string>ा</string>
			<string>न</string>
      	</Stones>
    </Segment>
	<Segment SegmentTime="10" spawnIds="">
		
      	<MonsterRequiredLetters>
			<string>ल</string>
	  	<string>ा</string><string>न</string><string>ा</string></MonsterRequiredLetters>
	  	<MonsterAllLetters>
	  	</MonsterAllLetters>
	  	<Stones>
	        <string spawnId="4">त्र</string>
	        <string spawnId="57">ज्ञ</string>
	        <string spawnId="91">ल</string>
			<string spawnId="5">ा</string>
			<string spawnId="56">न</string>
			<string spawnId="92">ा</string>
      	</Stones>
	</Segment>
  </Segments>
</XMLLevel>