<XMLLevel CollectableMonster="" HideCallout="-1" LettersGroup="2" SegmentTime="11" StoneType="1" monsterInputType="LetterInWord">
  <Segments>
    <Segment SegmentTime="11" spawnIds="">
      
	  <MonsterRequiredLetters>
		<string>e</string>
	  </MonsterRequiredLetters>
	  <MonsterAllLetters>
		<string>X</string>
		<string>g</string>
	  </MonsterAllLetters>
	  <Stones>
        <string spawnId="28">ng</string>
        <string spawnId="63">ngc</string>
        <string spawnId="25">p</string>
		<string spawnId="64">p</string>
		<string spawnId="91">nq</string>
        <string spawnId="92">e</string>
		<string spawnId="60">MagnetLetter</string>
      </Stones>
    </Segment>
	<Segment SegmentTime="11" spawnIds="">
      
	  <MonsterRequiredLetters>
		<string>t</string>
	  </MonsterRequiredLetters>
	  <MonsterAllLetters>
		<string>X</string>
		<string>s</string>
		<string>h</string>
	  <string>e</string></MonsterAllLetters>
	  <Stones>
        <string spawnId="3">tsh</string>
        <string spawnId="59">ngc</string>
        <string spawnId="2">ng</string>
		<string spawnId="61">gc</string>
		<string spawnId="54">e</string>
        <string spawnId="55">t</string>
      </Stones>
    </Segment>
	<Segment SegmentTime="11" spawnIds="">
      
	  <MonsterRequiredLetters>
		<string>ng</string>
	  </MonsterRequiredLetters>
	  <MonsterAllLetters>
		<string>X</string>
		<string>c</string>
		<string>o</string>
	  </MonsterAllLetters>
	  <Stones>
        <string spawnId="16">ng</string>
        <string spawnId="80">ng</string>
        <string spawnId="66">gc</string>
		<string spawnId="77">tsh</string>
		<string spawnId="67">t</string>
        <string spawnId="17">ng</string>
      </Stones>
    </Segment>
	<Segment SegmentTime="11" spawnIds="">
      
	  <MonsterRequiredLetters>
		<string>tsh</string>
	  </MonsterRequiredLetters>
	  <MonsterAllLetters>
		<string>X</string>
		<string>e</string>
		</MonsterAllLetters>
	  <Stones>
        <string spawnId="77">ng</string>
        <string spawnId="17">e</string>
        <string spawnId="67">nx</string>
		<string spawnId="16">p</string>
		<string spawnId="66">ng</string>
		<string spawnId="80">tsh</string>
      </Stones>
    </Segment>
	<Segment SegmentTime="11" spawnIds="2,3,90,89,93,94">
      
	  <MonsterRequiredLetters>
		<string>ngc</string>
	  </MonsterRequiredLetters>
	  <MonsterAllLetters>
		<string>X</string>
		<string>o</string>
		</MonsterAllLetters>
	  <Stones>
        <string>gc</string>
        <string>ng</string>
        <string>e</string>
		<string>ngc</string>
		<string>e</string>
		<string>ngc</string>
		<string bonusScore="125" chanceToShow="60" spawnId="86">BonusLetter</string>
		<string bonusScore="125" chanceToShow="60" spawnId="87">BonusLetter</string>
      </Stones>
    </Segment>
  </Segments>
</XMLLevel>