<XMLLevel CollectableMonster="" HideCallout="1" LettersGroup="5" SegmentTime="9" StoneType="1" monsterInputType="LetterInWord">
  <Segments>
    <Segment SegmentTime="9" spawnIds="">
      
	  <MonsterRequiredLetters>
		<string>b</string>
	  </MonsterRequiredLetters>
	  <MonsterAllLetters>
		<string>X</string>
		<string>o</string>
		<string>r</string>
	  <string>i</string></MonsterAllLetters>
	  <Stones>
        <string spawnId="55">s</string>
        <string spawnId="21">o</string>
        <string spawnId="85">s</string>
		<string spawnId="70">s</string>
		<string spawnId="60">w</string>
        <string spawnId="71">w</string>
		<string spawnId="88">w</string>
		<string spawnId="22">s</string>
		<string spawnId="54">b</string>
      </Stones>
    </Segment>
	<Segment SegmentTime="9" spawnIds="55,21,85,70,60,71,88,22,54">
      
	  <MonsterRequiredLetters>
		<string>k</string>
	  </MonsterRequiredLetters>
	  <MonsterAllLetters>
		<string>X</string>
		<string>o</string>
		<string>t</string>
	  <string>o</string></MonsterAllLetters>
	  <Stones>
        <string>o</string>
        <string>w</string>
        <string>b</string>
		<string>o</string>
		<string>o</string>
        <string>b</string>
		<string>o</string>
		<string>o</string>
		<string>k</string>
      </Stones>
    </Segment>
	<Segment SegmentTime="9" spawnIds="">
      
	  <MonsterRequiredLetters>
		<string>b</string>
	  </MonsterRequiredLetters>
	  <MonsterAllLetters>
		<string>X</string>
		<string>o</string>
		<string>r</string>
	  <string>i</string></MonsterAllLetters>
	  <Stones>
        <string spawnId="27">w</string>
        <string spawnId="64">k</string>
        <string spawnId="7">s</string>
		<string spawnId="24">s</string>
		<string spawnId="93">w</string>
        <string spawnId="6">s</string>
		<string spawnId="29">k</string>
		<string spawnId="94">s</string>
		<string spawnId="63">s</string>
		<string spawnId="26">b</string>
      </Stones>
    </Segment>
	<Segment SegmentTime="9" spawnIds="55,21,85,70,60,71,88,22,54">
      
	  <MonsterRequiredLetters>
		<string>k</string>
	  </MonsterRequiredLetters>
	  <MonsterAllLetters>
		<string>X</string>
		<string>o</string>
		<string>t</string>
		<string>o</string>
	  </MonsterAllLetters>
	  <Stones>
        <string>o</string>
        <string>o</string>
        <string>o</string>
		<string>b</string>
		<string>s</string>
		<string>s</string>
		<string>w</string>
		<string>s</string>
		<string>k</string>
      </Stones>
    </Segment>
	<Segment SegmentTime="9" spawnIds="55,21,85,70,60,71,88,22,54">
      
	  <MonsterRequiredLetters>
		<string>w</string>
	  </MonsterRequiredLetters>
	  <MonsterAllLetters>
		<string>X</string>
		<string>o</string>
		</MonsterAllLetters>
	  <Stones>
        <string>s</string>
        <string>o</string>
        <string>k</string>
		<string>k</string>
		<string>s</string>
		<string>k</string>
		<string>o</string>
		<string>o</string>
		<string>w</string>
      </Stones>
    </Segment>
  </Segments>
</XMLLevel>